boexplain/.DS_Store
boexplain/__init__.py
boexplain/files/.DS_Store
boexplain/files/.ipynb_checkpoints/Research_API-checkpoint.ipynb
boexplain/files/__init__.py
boexplain/files/cat_xform.py
boexplain/files/search.py
boexplain/files/stats.py
boexplain/files/tpe_wrapper.py
boexplain/optuna/.DS_Store
boexplain/optuna/.ipynb_checkpoints/optuna-checkpoint.ipynb
boexplain/optuna/__init__.py
boexplain/optuna/optuna/.DS_Store
boexplain/optuna/optuna/__init__.py
boexplain/optuna/optuna/_study_direction.py
boexplain/optuna/optuna/distributions.py
boexplain/optuna/optuna/exceptions.py
boexplain/optuna/optuna/logging.py
boexplain/optuna/optuna/progress_bar.py
boexplain/optuna/optuna/pruners/.DS_Store
boexplain/optuna/optuna/pruners/__init__.py
boexplain/optuna/optuna/pruners/base.py
boexplain/optuna/optuna/pruners/nop.py
boexplain/optuna/optuna/samplers/.DS_Store
boexplain/optuna/optuna/samplers/__init__.py
boexplain/optuna/optuna/samplers/_search_space.py
boexplain/optuna/optuna/samplers/base.py
boexplain/optuna/optuna/samplers/random.py
boexplain/optuna/optuna/samplers/tpe/__init__.py
boexplain/optuna/optuna/samplers/tpe/parzen_estimator.py
boexplain/optuna/optuna/samplers/tpe/sampler.py
boexplain/optuna/optuna/storages/__init__.py
boexplain/optuna/optuna/storages/base.py
boexplain/optuna/optuna/storages/in_memory.py
boexplain/optuna/optuna/structs.py
boexplain/optuna/optuna/study.py
boexplain/optuna/optuna/trial/__init__.py
boexplain/optuna/optuna/trial/_base.py
boexplain/optuna/optuna/trial/_fixed.py
boexplain/optuna/optuna/trial/_frozen.py
boexplain/optuna/optuna/trial/_state.py
boexplain/optuna/optuna/trial/_trial.py
boexplain/optuna/optuna/trial/_util.py
boexplain/optuna/setup.py
boexplain-0.1.1.dist-info/LICENSE
boexplain-0.1.1.dist-info/WHEEL
boexplain-0.1.1.dist-info/METADATA
boexplain-0.1.1.dist-info/RECORD
