Metadata-Version: 2.1
Name: boexplain
Version: 0.1.1
Summary: BOExplain
Home-page: https://github.com/sfu-db/BOExplain
License: MIT
Author: Brandon Lockhart
Author-email: brandon_lockhart@sfu.ca
Requires-Python: >=3.9,<4.0
Classifier: License :: OSI Approved :: MIT License
Classifier: Programming Language :: Python :: 3
Classifier: Programming Language :: Python :: 3.9
Requires-Dist: altair (==4.1.0)
Requires-Dist: colorlog (==4.4.0)
Requires-Dist: imblearn (==0.0)
Requires-Dist: numpy (==1.20.0)
Requires-Dist: numpyencoder (==0.3.0)
Requires-Dist: pandas (==1.2.1)
Requires-Dist: scikit-learn (==0.24.1)
Requires-Dist: scipy (==1.6.0)
Requires-Dist: tqdm (==4.51.0)
Project-URL: Repository, https://github.com/sfu-db/BOExplain
